swimport/__init__.py
swimport/__util__.py
swimport/all.py
swimport/containerswim.py
swimport/enumerationswim.py
swimport/functionswim.py
swimport/swim.py
swimport/swim_run.py
swimport/swim_run_paths.py
swimport/typedefswim.py
swimport/typeswim.py
swimport/variableswim.py
swimport/model/__init__.py
swimport/model/cpp_object.py
swimport/model/rules.py
swimport/pools/__init__.py
swimport/pools/complex_types.py
swimport/pools/pools.py
swimport/pools/types.py
swimport/pools/derived_types/__init__.py
swimport/pools/derived_types/array.py
swimport/pools/derived_types/callable_.py
swimport/pools/derived_types/iter_.py
swimport/pools/derived_types/map_.py
swimport/pools/derived_types/py_iterable.py
swimport/pools/derived_types/slice_.py
swimport/pools/derived_types/tuple_.py
swimport-3.1.1.dist-info/LICENSE
swimport-3.1.1.dist-info/METADATA
swimport-3.1.1.dist-info/WHEEL
swimport-3.1.1.dist-info/top_level.txt
swimport-3.1.1.dist-info/RECORD
