Metadata-Version: 2.1
Name: swimport
Version: 3.1.1
Summary: Swimport is a python library to simplify automate the meandering and error-prone parts of making a SWIG interface file for python
Home-page: https://github.com/talos-gis/swimport
Author: Ben Avrahami
Author-email: avrahami.ben@gmail.com
Maintainer: Idan Miara
Maintainer-email: idan@miara.com
License: MIT
Platform: UNKNOWN
Classifier: Development Status :: 4 - Beta
Classifier: Intended Audience :: Developers
Classifier: License :: OSI Approved :: MIT License
Classifier: Environment :: Win32 (MS Windows)
Classifier: Programming Language :: Python :: 3
Requires-Python: >=3.6.0
Requires-Dist: CppHeaderParser (>=2)
Provides-Extra: memory_testing
Requires-Dist: psutil ; extra == 'memory_testing'
